pip_mark_installed.py
pip_mark_installed-1.0.0.dist-info/METADATA
pip_mark_installed-1.0.0.dist-info/WHEEL
pip_mark_installed-1.0.0.dist-info/entry_points.txt
pip_mark_installed-1.0.0.dist-info/licenses/LICENSE.md
pip_mark_installed-1.0.0.dist-info/RECORD
