Metadata-Version: 2.4
Name: pip-mark-installed
Version: 1.0.0
Summary: Tool to mark packages as installed for pip without actually installing them.
Project-URL: Home, https://github.com/sitic/pip-mark-installed
Author-email: Jan Lebert <mail@janlebert.com>
License: Copyright (c) 2025 Jan Lebert
License-File: LICENSE.md
Classifier: Development Status :: 5 - Production/Stable
Classifier: Intended Audience :: Developers
Classifier: Intended Audience :: End Users/Desktop
Classifier: License :: OSI Approved :: MIT License
Classifier: Natural Language :: English
Classifier: Operating System :: OS Independent
Classifier: Programming Language :: Python :: 3
Classifier: Topic :: Software Development :: Build Tools
